sqlalchemy_dlock/.gitignore
sqlalchemy_dlock/__init__.py
sqlalchemy_dlock/_version.py
sqlalchemy_dlock/exceptions.py
sqlalchemy_dlock/factory.py
sqlalchemy_dlock/py.typed
sqlalchemy_dlock/registry.py
sqlalchemy_dlock/typing.py
sqlalchemy_dlock/lock/__init__.py
sqlalchemy_dlock/lock/base.py
sqlalchemy_dlock/lock/mysql.py
sqlalchemy_dlock/lock/postgresql.py
sqlalchemy_dlock/statement/__init__.py
sqlalchemy_dlock/statement/mysql.py
sqlalchemy_dlock/statement/postgresql.py
sqlalchemy_dlock-0.7.0.dist-info/licenses/LICENSE
sqlalchemy_dlock-0.7.0.dist-info/METADATA
sqlalchemy_dlock-0.7.0.dist-info/WHEEL
sqlalchemy_dlock-0.7.0.dist-info/top_level.txt
sqlalchemy_dlock-0.7.0.dist-info/RECORD
