Metadata-Version: 2.4
Name: sqlalchemy-dlock
Version: 0.7.0
Summary: A distributed lock implementation based on SQLAlchemy
Author-email: liu xue yan <liu_xue_yan@foxmail.com>
License-Expression: BSD-3-Clause
Project-URL: homepage, https://github.com/tanbro/sqlalchemy-dlock
Project-URL: documentation, https://sqlalchemy-dlock.readthedocs.io/
Project-URL: repository, https://github.com/tanbro/sqlalchemy-dlock.git
Keywords: SQLAlchemy,lock,distributed,distributed lock,SQL,database,DBMS,RDBMS
Classifier: Development Status :: 5 - Production/Stable
Classifier: Topic :: Database :: Front-Ends
Classifier: Intended Audience :: Developers
Classifier: Programming Language :: Python
Requires-Python: >=3.9
License-File: LICENSE
Requires-Dist: SQLAlchemy[asyncio]<3.0,>=1.4.3
Requires-Dist: typing-extensions; python_version < "3.12"
Provides-Extra: mysqlclient
Requires-Dist: mysqlclient; extra == "mysqlclient"
Provides-Extra: pymysql
Requires-Dist: pymysql; extra == "pymysql"
Provides-Extra: aiomysql
Requires-Dist: aiomysql; extra == "aiomysql"
Provides-Extra: psycopg2
Requires-Dist: psycopg2>=2.8; extra == "psycopg2"
Provides-Extra: psycopg2-binary
Requires-Dist: psycopg2-binary>=2.8; extra == "psycopg2-binary"
Provides-Extra: psycopg3
Requires-Dist: psycopg; extra == "psycopg3"
Provides-Extra: psycopg3-binary
Requires-Dist: psycopg[binary]; extra == "psycopg3-binary"
Provides-Extra: psycopg3-c
Requires-Dist: psycopg[c]; extra == "psycopg3-c"
Provides-Extra: asyncpg
Requires-Dist: asyncpg; extra == "asyncpg"
Dynamic: license-file
